Metadata-Version: 2.1
Name: odoo-connector-2
Version: 1.0.5
Summary: This is a library that allow an easy and friendly connection with an Odoo ERP instance on Pyhton 3.x
Home-page: https://github.com/franklintiel/odoo-connector-2/wiki
Author: Franklin Sarmiento
Author-email: franklinitiel@gmail.com
License: MIT
Project-URL: Documentation, https://github.com/franklintiel/odoo-connector-2
Project-URL: Source, https://github.com/franklintiel/odoo-connector-2/
Project-URL: Tracker, https://github.com/franklintiel/odoo-connector-2/issues
Keywords: odoo connector connect interface connection odoo_connection odoo_connect odoo_connector odoo_interface odoo_protocol
Platform: UNKNOWN
Classifier: Development Status :: 5 - Production/Stable
Classifier: License :: OSI Approved :: MIT License
Classifier: Programming Language :: Python :: 3.6
Requires-Python: >=3.*
